irishrail/__init__.py
irishrail/api.py
irishrail/cli.py
irishrail/commands/__init__.py
irishrail/commands/live.py
irishrail/commands/stations.py
irishrail-0.1.0.dist-info/entry_points.txt
irishrail-0.1.0.dist-info/WHEEL
irishrail-0.1.0.dist-info/METADATA
irishrail-0.1.0.dist-info/RECORD
