Metadata-Version: 2.1
Name: irishrail
Version: 0.1.0
Summary: 
Home-page: https://github.com/rougeth/irishrail
Author: Marco Rougeth
Author-email: rougeth@users.noreply.github.com
Requires-Python: >=3.8,<4.0
Classifier: Programming Language :: Python :: 3
Classifier: Programming Language :: Python :: 3.10
Classifier: Programming Language :: Python :: 3.8
Classifier: Programming Language :: Python :: 3.9
Requires-Dist: click (>=8.1.3,<9.0.0)
Requires-Dist: httpx (>=0.23.0,<0.24.0)
Requires-Dist: rich (>=12.4.4,<13.0.0)
Requires-Dist: xmltodict (>=0.13.0,<0.14.0)
